agent_6tisch/__init__.py
agent_6tisch/agent.py
agent_6tisch/env.py
agent_6tisch/msg.py
agent_6tisch-0.0.8.dist-info/DESCRIPTION.rst
agent_6tisch-0.0.8.dist-info/METADATA
agent_6tisch-0.0.8.dist-info/RECORD
agent_6tisch-0.0.8.dist-info/WHEEL
agent_6tisch-0.0.8.dist-info/metadata.json
agent_6tisch-0.0.8.dist-info/top_level.txt
