Metadata-Version: 2.0
Name: agent-6tisch
Version: 0.0.8
Summary: 6TiSCH agent for F-Interop
Home-page: UNKNOWN
Author: Rémy Léone
Author-email: remy.leone@inria.fr
License: BSD
Platform: UNKNOWN
Classifier: License :: OSI Approved :: MIT License
Classifier: Programming Language :: Python
Classifier: Programming Language :: Python :: 2.6
Classifier: Programming Language :: Python :: 2.7
Classifier: Programming Language :: Python :: Implementation :: CPython
Requires-Dist: cc2538
Requires-Dist: cerberus
Requires-Dist: pika
Requires-Dist: pyserial
Requires-Dist: pyzmq
Requires-Dist: telosb
